pyGitConnect.py
pygitconnect-0.1.2.dist-info/LICENSE
pygitconnect-0.1.2.dist-info/WHEEL
pygitconnect-0.1.2.dist-info/METADATA
pygitconnect-0.1.2.dist-info/RECORD
