Metadata-Version: 2.1
Name: pygitconnect
Version: 0.1.2
Summary: Simple API interface for more convenient work with GitHub service
Home-page: https://github.com/tankalxat34/pyGitConnect
License: MIT
Keywords: github,git,package
Author: tankalxat34
Author-email: tankalxat34@gmail.com
Requires-Python: >=3.7,<4.0
Classifier: License :: OSI Approved :: MIT License
Classifier: Programming Language :: Python :: 3
Classifier: Programming Language :: Python :: 3.10
Classifier: Programming Language :: Python :: 3.7
Classifier: Programming Language :: Python :: 3.8
Classifier: Programming Language :: Python :: 3.9
Requires-Dist: requests (>=2.20.0,<3.0.0)
Project-URL: Repository, https://github.com/tankalxat34/pyGitConnect
